vibeflux/__init__.py
vibeflux/cli.py
vibeflux/registry.py
vibeflux/algorithms/__init__.py
vibeflux/algorithms/base.py
vibeflux/gui/__init__.py
vibeflux/gui/main_window.py
vibeflux-0.0.2.dist-info/licenses/LICENSE
vibeflux-0.0.2.dist-info/METADATA
vibeflux-0.0.2.dist-info/WHEEL
vibeflux-0.0.2.dist-info/entry_points.txt
vibeflux-0.0.2.dist-info/top_level.txt
vibeflux-0.0.2.dist-info/RECORD
